{
	"name": "Дом Михляева",
	"images": [
		"https://avatars.mds.yandex.net/get-snippets_images/1042482/rth6ab2486f91a786bafa1ed71fc0a80763/828x620",
		"https://avatars.mds.yandex.net/get-turbo/4323936/rth598edb1b3005564ddf9d893359675ddb/max_g480_c12_r2x3_pd20",
		"https://avatars.mds.yandex.net/get-snippets_images/1064939/rthb124c176d4e592debeb1abd5860344f1/828x620"
	],
	"description": "Дом Михляева — единственный в Казани памятник гражданской архитектуры петровской эпохи и единственный каменный дом в Казани, по данным 1739 года. Достоверно известно, что именно в этом доме жил Петр Первый когда был в Казани в 1722 году. Иван Афанасьевич Михляев — купец и промышленник, владелец суконной мануфактуры, кожевенного и винокуренного заводов в Казани, совладелец полотняного завода в Москве. Документами доказано, что Петр пребывал в Казани 2–6 июня 1722 года и ночевал на своей галере, а днём ездил в город. 4 и 5 июня государь знакомился с кожевенными и суконными предприятиями. Осмотрев суконные фабрики, казённую и частную, Пётр остался доволен устройством мануфактуры Михляева и передал ему казённую фабрику со строениями, людьми и материалами. После этого Пётр посетил дом Михляева. По преданию, хозяин отблагодарил государя \"двумя большими подносами золота\".",
	"coordinates": {
		"latitude": 55.793057,
		"longitude": 49.113062
	},
	"address": "Казань, Республика Татарстан, Профсоюзная улица, 3"
}
